{
  "synthetic": true,
  "requirementId": "REQ-TASK-002",
  "class": "HAPPY",
  "cases": [
    {
      "name": "opened+queued+assigned lands exactly one accountable owner (AC1/AC2)",
      "op": "ownership",
      "open": {
        "workItemId": "wi-fx-002-h",
        "origin": "thread",
        "subjectRef": "thread:th-fx",
        "purpose": "member-message",
        "risk": "routine",
        "serviceTier": "concierge",
        "slaPolicyId": "sla-concierge",
        "policyVersion": 1,
        "responseDueAt": "2026-03-02T09:00:00Z",
        "poolId": null,
        "openedAt": "2026-03-02T08:00:00Z"
      },
      "log": [
        {
          "workItemId": "wi-fx-002-h",
          "eventSeq": 1,
          "eventType": "opened",
          "occurredAt": "2026-03-02T08:00:00Z"
        },
        {
          "workItemId": "wi-fx-002-h",
          "eventSeq": 2,
          "eventType": "queued",
          "occurredAt": "2026-03-02T08:00:00Z"
        },
        {
          "workItemId": "wi-fx-002-h",
          "eventSeq": 3,
          "eventType": "assigned",
          "occurredAt": "2026-03-02T08:05:00Z",
          "toOwnerRef": "synthetic-guide:william",
          "reason": "assignment"
        }
      ],
      "expectOwner": "synthetic-guide:william",
      "expectStatus": "open",
      "expectFirstOwned": true
    },
    {
      "name": "a claim is an ownership-acceptance action (AC2)",
      "op": "acceptance",
      "eventType": "claimed",
      "expectAcceptance": true
    },
    {
      "name": "an assignment is an ownership-acceptance action (AC2)",
      "op": "acceptance",
      "eventType": "assigned",
      "expectAcceptance": true
    }
  ]
}
